numeric_grad/__init__.py
numeric_grad/numeric_grad.py
ngram_ml-0.1.0.dist-info/METADATA
ngram_ml-0.1.0.dist-info/WHEEL
ngram_ml-0.1.0.dist-info/top_level.txt
ngram_ml-0.1.0.dist-info/RECORD
