Metadata-Version: 2.1
Name: ngram-ml
Version: 0.1.0
Summary: Basic python package for creating n-gram language models from text files
Home-page: https://github.com/anil-gurbuz/ngram_ml
Author: Anil Gurbuz
Author-email: anlgrbz91@gmail.com
License: MIT
Keywords: NLP,ngram,MLE,Simple Language Model,Neural Network
Platform: UNKNOWN
Classifier: Development Status :: 2 - Pre-Alpha
Classifier: Intended Audience :: Developers
Classifier: Intended Audience :: Education
Classifier: Operating System :: OS Independent
Classifier: License :: OSI Approved :: MIT License
Classifier: Programming Language :: Python :: 3
Requires-Dist: requests
Requires-Dist: numpy
